codelytics/__init__.py
codelytics/dir.py
codelytics/helpers.py
codelytics/names.py
codelytics/notebook.py
codelytics/pdf.py
codelytics/py.py
codelytics/text_analysis.py
codelytics-2025.7.2.dist-info/METADATA
codelytics-2025.7.2.dist-info/WHEEL
codelytics-2025.7.2.dist-info/licenses/LICENSE
codelytics-2025.7.2.dist-info/RECORD
