Metadata-Version: 2.4
Name: codelytics
Version: 2025.7.2
Summary: A Python package for extracting code and text metrics in Python projects.
Project-URL: Repository, https://github.com/teachnology/codelytics
Author-email: marijanbeg <m.beg@imperial.ac.uk>
License-Expression: MIT
License-File: LICENSE
Keywords: Jupyter,Python,Python package,assessment,automation,code analysis,code metrics,code quality,coursework,generative AI,github,higher education,linting,repositories
Classifier: Development Status :: 5 - Production/Stable
Classifier: Intended Audience :: Education
Classifier: License :: OSI Approved :: MIT License
Classifier: Natural Language :: English
Classifier: Operating System :: OS Independent
Requires-Python: >=3.13
Requires-Dist: complexipy>=3.0.0
Requires-Dist: nbformat>=5.10.4
Requires-Dist: pandas>=2.3.0
Requires-Dist: pymupdf>=1.26.1
Requires-Dist: pyspellchecker>=0.8.3
Requires-Dist: radon>=6.0.1
